pytest_expectr/__init__.py
pytest_expectr/plugin.py
pytest_expectr-1.4.2.dist-info/LICENSE
pytest_expectr-1.4.2.dist-info/METADATA
pytest_expectr-1.4.2.dist-info/WHEEL
pytest_expectr-1.4.2.dist-info/entry_points.txt
pytest_expectr-1.4.2.dist-info/top_level.txt
pytest_expectr-1.4.2.dist-info/RECORD
