Metadata-Version: 2.1
Name: pytest-expectr
Version: 1.4.2
Summary: This plugin is used to expect multiple assert using pytest framework.
Home-page: https://github.com/Benabra/pytest_expectr
Author: Jihad BENABRA
Author-email: jihadbenabra@gmail.com
License: Mozilla Public License 2.0 (MPL 2.0)
Keywords: py.test pytest json variables
Platform: UNKNOWN
Classifier: Framework :: Pytest
Requires-Dist: pytest (>=2.4.2)
